denmune/__init__.py
denmune/denmune.py
pymune-0.0.12.dist-info/LICENSE
pymune-0.0.12.dist-info/METADATA
pymune-0.0.12.dist-info/WHEEL
pymune-0.0.12.dist-info/top_level.txt
pymune-0.0.12.dist-info/RECORD
